stuart_dataops/__init__.py
stuart_dataops/dataops.py
stuart_dataops-0.1.1.dist-info/LICENSE.txt
stuart_dataops-0.1.1.dist-info/METADATA
stuart_dataops-0.1.1.dist-info/WHEEL
stuart_dataops-0.1.1.dist-info/top_level.txt
stuart_dataops-0.1.1.dist-info/RECORD
